stockprice/__init__.py
stockprice/get_ticker_statistics.py
stockprice/main.py
stockprice_cli-2.2.0.dist-info/METADATA
stockprice_cli-2.2.0.dist-info/WHEEL
stockprice_cli-2.2.0.dist-info/entry_points.txt
stockprice_cli-2.2.0.dist-info/top_level.txt
stockprice_cli-2.2.0.dist-info/RECORD
