Metadata-Version: 2.1
Name: stockprice-cli
Version: 2.2.0
Summary: UNKNOWN
Home-page: https://github.com/Thomas-mcinally/stockprice
Author: Thomas Mcinally
License: UNKNOWN
Platform: UNKNOWN
Requires-Python: >=3.7
Requires-Dist: requests ==2.28.2
Requires-Dist: charset-normalizer ==3.1.0 ; python_full_version >= "3.7.0"
Requires-Dist: urllib3 ==1.26.14 ; python_version >= "2.7" and python_version not in "3.0, 3.1, 3.2, 3.3, 3.4, 3.5"
Requires-Dist: idna ==3.4 ; python_version >= "3.5"
Requires-Dist: certifi ==2022.12.7 ; python_version >= "3.6"
